pymatdet/__init__.py
pymatdet/main.py
pymatdet-2.0.1.dist-info/LICENSE
pymatdet-2.0.1.dist-info/METADATA
pymatdet-2.0.1.dist-info/WHEEL
pymatdet-2.0.1.dist-info/top_level.txt
pymatdet-2.0.1.dist-info/RECORD
