Metadata-Version: 2.1
Name: pymatdet
Version: 2.0.1
Summary: This is a module which can be used for performing matrix operations
Author-email: Viren Tanti <virentanti16@gmail.com>
License: MIT License
Project-URL: Homepage, https://github.com/Virentanti/pymatdet
Project-URL: Bug Tracker, https://github.com/Virentanti/pymatdet/issues
Classifier: Programming Language :: Python :: 3
Classifier: License :: OSI Approved :: MIT License
Classifier: Operating System :: OS Independent
Requires-Python: >=3.6
License-File: LICENSE
